pan_omic_consciousness_engine-1.0.0a0.dist-info/licenses/LICENSE
pce/__init__.py
pce/cis/__init__.py
pce/cli/__init__.py
pce/core/__init__.py
pce/core/config.py
pce/core/datatypes.py
pce/core/registry.py
pce/core/scheduler.py
pce/data/__init__.py
pce/data/ingestion.py
pce/data/toy_datasets.py
pce/data/transforms.py
pce/e3de/__init__.py
pce/hdts/__init__.py
pce/mogil/__init__.py
pce/mogil/gnn_models.py
pce/mogil/hypergraph.py
pce/qlem/__init__.py
pce/utils/__init__.py
pce/utils/logging.py
pce/utils/metrics.py
pce/utils/seed.py
tests/__init__.py
tests/conftest.py
tests/test_pce.py
pan_omic_consciousness_engine-1.0.0a0.dist-info/METADATA
pan_omic_consciousness_engine-1.0.0a0.dist-info/WHEEL
pan_omic_consciousness_engine-1.0.0a0.dist-info/entry_points.txt
pan_omic_consciousness_engine-1.0.0a0.dist-info/top_level.txt
pan_omic_consciousness_engine-1.0.0a0.dist-info/RECORD
