Metadata-Version: 2.4
Name: pan-omic-consciousness-engine
Version: 1.0.0a0
Summary: Pan-Omics Consciousness Engine - A computational framework for modeling consciousness emergence
Home-page: https://github.com/krish567366/pan-omic
Author: Krishna Bajpai and Veddanshi Gupta
Author-email: Krishna Bajpai <krishna@krishna.me>, Veddanshi Gupta <krishna@krishna.me>
Maintainer-email: Krishna Bajpai <krishna@krishna.me>, Veddanshi Gupta <krishna@krishna.me>
License: Apache License
Project-URL: Homepage, https://github.com/krish567366/pan-omic
Project-URL: Documentation, https://krish567366.github.io/pan-omic/
Project-URL: Repository, https://github.com/krish567366/pan-omic
Project-URL: Bug Tracker, https://github.com/krish567366/pan-omic/issues
Keywords: bioinformatics,omics,consciousness,digital-twin,quantum,entropy
Platform: any
Classifier: Development Status :: 4 - Beta
Classifier: Intended Audience :: Science/Research
Classifier: License :: OSI Approved :: Apache Software License
Classifier: Operating System :: OS Independent
Classifier: Programming Language :: Python :: 3
Classifier: Programming Language :: Python :: 3.10
Classifier: Programming Language :: Python :: 3.11
Classifier: Programming Language :: Python :: 3.12
Classifier: Topic :: Scientific/Engineering :: Bio-Informatics
Classifier: Topic :: Scientific/Engineering :: Artificial Intelligence
Requires-Python: >=3.8
License-File: LICENSE
Requires-Dist: numpy>=1.24.0
Requires-Dist: scipy>=1.11.0
Requires-Dist: pandas>=2.0.0
Requires-Dist: networkx>=3.1
Requires-Dist: torch>=2.0.0
Requires-Dist: torch-geometric>=2.3.0
Requires-Dist: pydantic>=2.0.0
Requires-Dist: fastapi>=0.100.0
Requires-Dist: uvicorn[standard]>=0.23.0
Requires-Dist: typer>=0.9.0
Requires-Dist: rich>=13.0.0
Requires-Dist: tqdm>=4.65.0
Requires-Dist: matplotlib>=3.7.0
Requires-Dist: seaborn>=0.12.0
Requires-Dist: scikit-learn>=1.3.0
Requires-Dist: biopython>=1.81
Requires-Dist: h5py>=3.9.0
Requires-Dist: zarr>=2.16.0
Requires-Dist: tensorboard>=2.13.0
Requires-Dist: wandb>=0.15.0
Requires-Dist: hydra-core>=1.3.0
Requires-Dist: omegaconf>=2.3.0
Provides-Extra: dev
Requires-Dist: pytest>=7.4.0; extra == "dev"
Requires-Dist: pytest-cov>=4.1.0; extra == "dev"
Requires-Dist: pytest-asyncio>=0.21.0; extra == "dev"
Requires-Dist: pytest-mock>=3.11.0; extra == "dev"
Requires-Dist: black>=23.7.0; extra == "dev"
Requires-Dist: ruff>=0.0.280; extra == "dev"
Requires-Dist: mypy>=1.5.0; extra == "dev"
Requires-Dist: pre-commit>=3.3.0; extra == "dev"
Requires-Dist: mkdocs>=1.5.0; extra == "dev"
Requires-Dist: mkdocs-material>=9.1.0; extra == "dev"
Requires-Dist: mkdocstrings[python]>=0.22.0; extra == "dev"
Requires-Dist: mkdocs-gen-files>=0.5.0; extra == "dev"
Requires-Dist: mkdocs-git-revision-date-localized-plugin>=1.2.0; extra == "dev"
Provides-Extra: docs
Requires-Dist: mkdocs>=1.5.0; extra == "docs"
Requires-Dist: mkdocs-material>=9.1.0; extra == "docs"
Requires-Dist: mkdocstrings[python]>=0.22.0; extra == "docs"
Requires-Dist: mkdocs-gen-files>=0.5.0; extra == "docs"
Requires-Dist: mkdocs-git-revision-date-localized-plugin>=1.2.0; extra == "docs"
Provides-Extra: quantum
Requires-Dist: qiskit>=0.44.0; extra == "quantum"
Requires-Dist: cirq>=1.2.0; extra == "quantum"
Requires-Dist: pennylane>=0.32.0; extra == "quantum"
Dynamic: author
Dynamic: home-page
Dynamic: license-file
Dynamic: platform
Dynamic: requires-python
